unmixing/__init__.py
unmixing/main.py
unmixing-0.2.0.dist-info/LICENSE
unmixing-0.2.0.dist-info/METADATA
unmixing-0.2.0.dist-info/WHEEL
unmixing-0.2.0.dist-info/top_level.txt
unmixing-0.2.0.dist-info/RECORD
