Metadata-Version: 2.1
Name: unmixing
Version: 0.2.0
License-File: LICENSE
Requires-Dist: torch
Requires-Dist: numpy
